Metadata-Version: 2.4
Name: cellprofiler-core-nightly
Version: 5.0.0.dev340
Summary: cellprofiler-core implements the bulk of CellProfiler's non-gui functionality
Author: Anne Carpenter, Thouis (Ray) Jones, Lee Kamentsky, Vebjorn Ljosa, David Logan, Mark Bray, Madison Swain-Bowden, Allen Goodman, Claire McQuinn, Alice Lucas, Callum Tromans-Coia
Author-email: Beth Cimini <bcimini@broadinstitute.org>, David Stirling <dstirling@glencoesoftware.com>, Nodar Gogoberidze <ngogober@broadinstitute.org>
Maintainer-email: Beth Cimini <bcimini@broadinstitute.org>, Nodar Gogoberidze <ngogober@broadinstitute.org>
License: The BSD 3-Clause License
Project-URL: Homepage, https://cellprofiler.org/
Project-URL: Documentation, https://cellprofiler.org/manuals
Project-URL: Wiki, https://github.com/CellProfiler/CellProfiler/wiki
Project-URL: Repository, https://github.com/CellProfiler/CellProfiler
Project-URL: Issues, https://github.com/CellProfiler/CellProfiler/issues
Project-URL: Changelog, https://github.com/CellProfiler/CellProfiler/releases
Keywords: computer vision,image analysis,biology,cell,cellprofiler
Classifier: Development Status :: 5 - Production/Stable
Classifier: Intended Audience :: Science/Research
Classifier: License :: OSI Approved :: BSD License
Classifier: Operating System :: OS Independent
Classifier: Programming Language :: Python :: 3.9
Classifier: Topic :: Scientific/Engineering :: Bio-Informatics
Classifier: Topic :: Scientific/Engineering :: Image Recognition
Classifier: Topic :: Scientific/Engineering :: Image Processing
Classifier: Topic :: Scientific/Engineering
Requires-Python: >=3.9
License-File: LICENSE
Requires-Dist: cellprofiler-library-nightly>=5.dev
Requires-Dist: boto3>=1.12.28
Requires-Dist: centrosome>=1.3.0
Requires-Dist: docutils>=0.15.2
Requires-Dist: future>=0.18.2
Requires-Dist: fsspec>=2021.11.0
Requires-Dist: h5py>=3.7.0
Requires-Dist: lxml>=4.6.4
Requires-Dist: matplotlib<4,>=3.1.3
Requires-Dist: numpy<2,>=1.24.4
Requires-Dist: psutil>=5.9.5
Requires-Dist: pyzmq>=22.3.0
Requires-Dist: scikit-image>=0.20.0
Requires-Dist: scipy<1.11,>=1.9.1
Requires-Dist: scyjava>=1.9.1
Requires-Dist: zarr>=2.16.1
Requires-Dist: google-cloud-storage~=2.10.0
Requires-Dist: packaging>=20.0
Provides-Extra: build
Requires-Dist: build; extra == "build"
Requires-Dist: pyinstaller; extra == "build"
Requires-Dist: twine; extra == "build"
Requires-Dist: sphinx>=3.1.1; extra == "build"
Requires-Dist: click>=7.1.2; extra == "build"
Provides-Extra: test
Requires-Dist: pytest~=7.4.1; extra == "test"
Requires-Dist: pytest-timeout~=2.1.0; extra == "test"
Provides-Extra: wx
Requires-Dist: wxPython==4.2.0; extra == "wx"
Dynamic: license-file
